clipify/__init__.py
clipify/audio/__init__.py
clipify/audio/extractor.py
clipify/audio/speech.py
clipify/core/__init__.py
clipify/core/ai_providers.py
clipify/core/clipify.py
clipify/core/processor.py
clipify/core/text_processor.py
clipify/video/__init__.py
clipify/video/converter.py
clipify/video/converterStretch.py
clipify/video/cutter.py
clipify/video/processor.py
clipify-2.1.4.dist-info/LICENSE
clipify-2.1.4.dist-info/METADATA
clipify-2.1.4.dist-info/WHEEL
clipify-2.1.4.dist-info/top_level.txt
clipify-2.1.4.dist-info/RECORD
