Metadata-Version: 2.1
Name: clipify
Version: 2.1.4
Summary: A powerful tool for processing video content into social media-friendly segments
Home-page: https://github.com/adelelawady/clipify
Author: Adel Elawady
Author-email: adel50ali50@gmail.com
Classifier: Programming Language :: Python :: 3
Classifier: License :: OSI Approved :: MIT License
Classifier: Operating System :: OS Independent
Requires-Python: >=3.8
License-File: LICENSE
Requires-Dist: captacity-clipify ==0.3.4
Requires-Dist: opencv-python ==4.8.0.74
Requires-Dist: moviepy ==1.0.3
Requires-Dist: numpy ==1.26.4
Requires-Dist: openai ==1.61.0
Requires-Dist: pydub ==0.25.1
Requires-Dist: requests ==2.31.0
Requires-Dist: setuptools ==49.2.1
Requires-Dist: textblob ==0.17.1
Requires-Dist: openai-whisper ==20231117
